bevy/config/__init__.py
bevy/config/config.py
bevy/config/config_file.py
bevy/config/directory_resolver.py
bevy/config/exceptions.py
bevy/config/file_reader.py
bevy/config/json_loader.py
bevy/config/loader.py
bevy/config/resolver.py
bevy/config/section_loader.py
bevy.config-0.1.2.dist-info/LICENSE
bevy.config-0.1.2.dist-info/WHEEL
bevy.config-0.1.2.dist-info/METADATA
bevy.config-0.1.2.dist-info/RECORD
