Metadata-Version: 2.1
Name: bevy.config
Version: 0.1.2
Summary: A config loader designed to be used with the Bevy dependency injection framework.
Home-page: https://github.com/ZechCodes/Bevy
License: MIT
Keywords: dependency,injection,annotations,types
Author: Zech Zimmerman
Author-email: hi@zech.codes
Requires-Python: >=3.7,<4.0
Classifier: Development Status :: 4 - Beta
Classifier: License :: OSI Approved :: MIT License
Classifier: Programming Language :: Python :: 3
Classifier: Programming Language :: Python :: 3.7
Classifier: Programming Language :: Python :: 3.8
Classifier: Programming Language :: Python :: 3.9
Classifier: Topic :: Software Development :: Libraries :: Application Frameworks
Project-URL: Documentation, https://github.com/ZechCodes/Bevy/blob/master/README.md
Project-URL: Repository, https://github.com/ZechCodes/Bevy
